{
  "schema_version": 1,
  "worker_id": "validator-dkr-4-v4",
  "status": "complete",
  "unit_id": "DKR-4",
  "checkpoint_disposition": "accepted_for_orchestrator_decision",
  "accepted_claim_count": 13,
  "rejected_claim_count": 0,
  "case_pass_count": 8,
  "case_target": 8,
  "explicit_port_count": 5,
  "controller_edge_count": 3,
  "max_observed_concurrency": 2,
  "activation_per_lease_violation_count": 0,
  "cross_session_leak_count": 0,
  "hidden_effect_edge_count": 0,
  "forbidden_public_surface_count": 0,
  "graceful_join_failure_count": 0,
  "resolved_evidence_hash_count": 10,
  "held_wall_count": 8,
  "held_wall_target": 8,
  "checkpoint_age_seconds": 264,
  "frame_max_age_seconds": 600,
  "assertion_source_in_universe": false,
  "verification_ref": "workers/validator-dkr-4-v4/verification.json",
  "replay_ref": "workers/validator-dkr-4-v4/replay.sh",
  "independent_audit_ref": "workers/validator-dkr-4-v4/independent-allowlist-audit.mjs",
  "next_authority": "orchestrator",
  "observed_at": "2026-07-15T06:17:20Z"
}
